submark/__init__.py
submark/cli.py
submark/submark.py
submark-0.7.dist-info/entry_points.txt
submark-0.7.dist-info/LICENSE
submark-0.7.dist-info/WHEEL
submark-0.7.dist-info/METADATA
submark-0.7.dist-info/RECORD
