Metadata-Version: 2.1
Name: submark
Version: 0.7
Summary: A Subset of Markdown
Home-page: https://github.com/okken/submark
License: UNKNOWN
Author: Brian Okken
Author-email: 
Classifier: License :: OSI Approved :: MIT License
Requires-Dist: pytest; extra == "test"
Requires-Dist: pytest-cov; extra == "test"
Requires-Dist: tox; extra == "test"
Provides-Extra: test
